chime_ml_build_tools/__init__.py
chime_ml_build_tools-0.0.1.dist-info/METADATA
chime_ml_build_tools-0.0.1.dist-info/WHEEL
chime_ml_build_tools-0.0.1.dist-info/top_level.txt
chime_ml_build_tools-0.0.1.dist-info/RECORD
