Metadata-Version: 2.1
Name: chime-ml-build-tools
Version: 0.0.1
Summary: x
Author: x
